mclumi/__init__.py
mclumi/bam/Build.py
mclumi/bam/Bundle.py
mclumi/bam/Reader.py
mclumi/bam/Relation.py
mclumi/bam/Writer.py
mclumi/bam/__init__.py
mclumi/deduplicate/Gadgetry.py
mclumi/deduplicate/Gene.py
mclumi/deduplicate/MultiPos.py
mclumi/deduplicate/OnePos.py
mclumi/deduplicate/SingleCell.py
mclumi/deduplicate/Tabulate.py
mclumi/deduplicate/__init__.py
mclumi/deduplicate/heterogeneity/Trace.py
mclumi/deduplicate/heterogeneity/__init__.py
mclumi/deduplicate/method/Adjacency.py
mclumi/deduplicate/method/Cluster.py
mclumi/deduplicate/method/Clustering.py
mclumi/deduplicate/method/Directional.py
mclumi/deduplicate/method/MarkovClustering.py
mclumi/deduplicate/method/ReformKit.py
mclumi/deduplicate/method/__init__.py
mclumi/deduplicate/pipeline/Heterogeneity.py
mclumi/deduplicate/pipeline/Simulation.py
mclumi/deduplicate/pipeline/__init__.py
mclumi/external/UMItoolsSamMethods.py
mclumi/external/__init__.py
mclumi/fastq/Convert.py
mclumi/fastq/Read.py
mclumi/fastq/Write.py
mclumi/fastq/__init__.py
mclumi/gene.py
mclumi/graph/Adjacency.py
mclumi/graph/CC.py
mclumi/graph/Edge.py
mclumi/graph/__init__.py
mclumi/graph/bfs/ConnectedComponent.py
mclumi/graph/bfs/__init__.py
mclumi/graph/dfs/Visit.py
mclumi/graph/dfs/__init__.py
mclumi/graph/undirected/__init__.py
mclumi/graph/undirected/unweighted/__init__.py
mclumi/graph/undirected/unweighted/repr/Adjacency.py
mclumi/graph/undirected/unweighted/repr/Edge.py
mclumi/graph/undirected/unweighted/repr/__init__.py
mclumi/graph/undirected/weighted/__init__.py
mclumi/graph/undirected/weighted/repr/Adjacency.py
mclumi/graph/undirected/weighted/repr/__init__.py
mclumi/main.py
mclumi/multipos.py
mclumi/onepos.py
mclumi/path.py
mclumi/prep.py
mclumi/sc.py
mclumi/util/Console.py
mclumi/util/Folder.py
mclumi/util/Hamming.py
mclumi/util/Number.py
mclumi/util/Parameter.py
mclumi/util/Reader.py
mclumi/util/Single.py
mclumi/util/Writer.py
mclumi/util/__init__.py
mclumi-0.0.4.dist-info/LICENSE
mclumi-0.0.4.dist-info/METADATA
mclumi-0.0.4.dist-info/WHEEL
mclumi-0.0.4.dist-info/entry_points.txt
mclumi-0.0.4.dist-info/RECORD
