Metadata-Version: 2.1
Name: mclumi
Version: 0.0.4
Summary: UMI de-duplication using mclUMI
Home-page: https://cribbslab.co.uk/
License: MIT
Keywords: packaging,mclumi
Author: Jianfeng Sun
Maintainer: Jianfeng Sun
Maintainer-email: jianfeng.sun@ndorms.ox.ac.uk
Requires-Python: >=3.10,<4.0
Classifier: License :: OSI Approved :: MIT License
Classifier: Programming Language :: Python :: 3
Classifier: Programming Language :: Python :: 3.10
Classifier: Programming Language :: Python :: 3.11
Classifier: Programming Language :: Python :: 3.12
Requires-Dist: click (>=8.1.7,<9.0.0)
Requires-Dist: markov-clustering
Requires-Dist: numpy (>=1.26.2,<2.0.0)
Requires-Dist: pandas (>=2.1.4,<3.0.0)
Requires-Dist: pyfastx (>=2.0.2,<3.0.0)
Requires-Dist: pyfiglet (>=1.0.2,<2.0.0)
Requires-Dist: pysam (>=0.22.0,<0.23.0)
Requires-Dist: pyyaml (>=6.0.1,<7.0.0)
Requires-Dist: scikit-learn (>=1.3.2,<2.0.0)
Project-URL: Repository, https://github.com/cribbslab/mclumi
